urzad_regulacji_energetyki/__init__.py
urzad_regulacji_energetyki/biuletyn_informacji_publicznej_changelog/__init__.py
urzad_regulacji_energetyki/biuletyn_informacji_publicznej_changelog/analyzer.py
urzad_regulacji_energetyki/biuletyn_informacji_publicznej_changelog/models.py
urzad_regulacji_energetyki/biuletyn_informacji_publicznej_changelog/scrapers.py
urzad_regulacji_energetyki/biuletyn_informacji_publicznej_changelog/utils.py
urzad_regulacji_energetyki/rejestr_mioze/__init__.py
urzad_regulacji_energetyki/rejestr_mioze/models.py
urzad_regulacji_energetyki/rejestr_mioze/registry.py
urzad_regulacji_energetyki/rejestr_mioze/scrapers.py
urzad_regulacji_energetyki/rejestr_mioze/utils.py
urzad_regulacji_energetyki/taryfy_i_inne_decyzje_energia_elektryczna/__init__.py
urzad_regulacji_energetyki/taryfy_i_inne_decyzje_energia_elektryczna/analyzer.py
urzad_regulacji_energetyki/taryfy_i_inne_decyzje_energia_elektryczna/models.py
urzad_regulacji_energetyki/taryfy_i_inne_decyzje_energia_elektryczna/scrapers.py
urzad_regulacji_energetyki/taryfy_i_inne_decyzje_energia_elektryczna/utils.py
urzad_regulacji_energetyki-0.0.3.dist-info/licenses/LICENSE
urzad_regulacji_energetyki-0.0.3.dist-info/METADATA
urzad_regulacji_energetyki-0.0.3.dist-info/WHEEL
urzad_regulacji_energetyki-0.0.3.dist-info/top_level.txt
urzad_regulacji_energetyki-0.0.3.dist-info/RECORD
