Metadata-Version: 2.4
Name: urzad-regulacji-energetyki
Version: 0.0.3
Summary: A library for creating insights from publicly available data on the Polish Energy Regulatory Office (URE)
Author-email: Wiktor Hawrylik <wiktor.hawrylik@gmail.com>
Maintainer-email: Wiktor Hawrylik <wiktor.hawrylik@gmail.com>
License-Expression: GPL-3.0
Project-URL: Homepage, https://github.com/WiktorHawrylik/urzad-regulacji-energetyki
Project-URL: Repository, https://github.com/WiktorHawrylik/urzad-regulacji-energetyki
Project-URL: Documentation, https://wiktorhawrylik.github.io/urzad-regulacji-energetyki/
Project-URL: Bug Tracker, https://github.com/WiktorHawrylik/urzad-regulacji-energetyki/issues
Classifier: Development Status :: 3 - Alpha
Classifier: Intended Audience :: Developers
Classifier: Programming Language :: Python :: 3
Classifier: Programming Language :: Python :: 3.9
Classifier: Programming Language :: Python :: 3.10
Classifier: Programming Language :: Python :: 3.11
Classifier: Programming Language :: Python :: 3.12
Requires-Python: >=3.9
License-File: LICENSE
Requires-Dist: requests>=2.31.0
Requires-Dist: beautifulsoup4>=4.12.0
Requires-Dist: pandas>=2.0.0
Requires-Dist: numpy>=1.24.0
Requires-Dist: lxml>=4.9.0
Requires-Dist: pydantic>=2.0.0
Requires-Dist: python-dateutil>=2.8.0
Provides-Extra: dev
Requires-Dist: pytest>=7.4.0; extra == "dev"
Requires-Dist: pytest-cov>=4.1.0; extra == "dev"
Requires-Dist: pytest-xdist>=3.3.0; extra == "dev"
Requires-Dist: ruff>=0.8.0; extra == "dev"
Requires-Dist: mypy>=1.5.0; extra == "dev"
Requires-Dist: pre-commit>=3.3.0; extra == "dev"
Requires-Dist: pandas-stubs>=2.0.0; extra == "dev"
Requires-Dist: types-requests>=2.31.0; extra == "dev"
Requires-Dist: types-beautifulsoup4>=4.12.0; extra == "dev"
Provides-Extra: docs
Requires-Dist: mkdocs>=1.5.0; extra == "docs"
Requires-Dist: mkdocs-material>=9.5.0; extra == "docs"
Requires-Dist: mkdocstrings[python]>=0.24.0; extra == "docs"
Requires-Dist: mike>=2.0.0; extra == "docs"
Provides-Extra: test
Requires-Dist: pytest>=7.4.0; extra == "test"
Requires-Dist: pytest-cov>=4.1.0; extra == "test"
Requires-Dist: pytest-xdist>=3.3.0; extra == "test"
Requires-Dist: pytest-mock>=3.11.0; extra == "test"
Requires-Dist: responses>=0.23.0; extra == "test"
Dynamic: license-file
